crucible/__init__.py
crucible/async_client.py
crucible/client.py
crucible/config.py
crucible/errors.py
crucible/genai_async_client.py
crucible/genai_client.py
crucible/langchain_llm.py
crucible/logger.py
crucible/streaming.py
crucible/types.py
crucible/api/__init__.py
crucible/api/client.py
crucible_ai_sdk-0.0.27.dist-info/METADATA
crucible_ai_sdk-0.0.27.dist-info/WHEEL
crucible_ai_sdk-0.0.27.dist-info/entry_points.txt
crucible_ai_sdk-0.0.27.dist-info/top_level.txt
crucible_ai_sdk-0.0.27.dist-info/RECORD
