Metadata-Version: 2.4
Name: crucible-ai-sdk
Version: 0.0.27
Summary: A high-performance Python SDK for logging and monitoring OpenAI API calls to Crucible
Author-email: Crucible Team <support@crucible.ai>
Maintainer-email: Crucible Team <support@crucible.ai>
License-Expression: MIT
Project-URL: Homepage, https://crucible.ai
Project-URL: Documentation, https://docs.crucible.ai
Project-URL: Repository, https://github.com/crucible/crucible-python-sdk
Project-URL: Issues, https://github.com/crucible/crucible-python-sdk/issues
Project-URL: Changelog, https://github.com/crucible/crucible-python-sdk/blob/main/CHANGELOG.md
Keywords: openai,logging,monitoring,ai,llm,observability
Classifier: Development Status :: 3 - Alpha
Classifier: Intended Audience :: Developers
Classifier: Operating System :: OS Independent
Classifier: Programming Language :: Python :: 3
Classifier: Programming Language :: Python :: 3.8
Classifier: Programming Language :: Python :: 3.9
Classifier: Programming Language :: Python :: 3.10
Classifier: Programming Language :: Python :: 3.11
Classifier: Programming Language :: Python :: 3.12
Classifier: Topic :: Software Development :: Libraries :: Python Modules
Classifier: Topic :: Scientific/Engineering :: Artificial Intelligence
Requires-Python: >=3.8
Requires-Dist: openai>=1.0.0
Requires-Dist: httpx>=0.24.0
Requires-Dist: pydantic>=2.0.0
Provides-Extra: dev
Requires-Dist: pytest>=7.0.0; extra == "dev"
Requires-Dist: pytest-asyncio>=0.21.0; extra == "dev"
Requires-Dist: pytest-mock>=3.10.0; extra == "dev"
Requires-Dist: black>=23.0.0; extra == "dev"
Requires-Dist: isort>=5.12.0; extra == "dev"
Requires-Dist: flake8>=6.0.0; extra == "dev"
Requires-Dist: mypy>=1.0.0; extra == "dev"
Provides-Extra: test
Requires-Dist: pytest>=7.0.0; extra == "test"
Requires-Dist: pytest-asyncio>=0.21.0; extra == "test"
Requires-Dist: pytest-mock>=3.10.0; extra == "test"
Requires-Dist: pytest-cov>=4.0.0; extra == "test"
Requires-Dist: python-dotenv>=1.0.0; extra == "test"
Provides-Extra: langchain
Requires-Dist: langchain-community>=0.0.1; extra == "langchain"
Requires-Dist: langchain>=0.1.0; extra == "langchain"
Provides-Extra: genai
Requires-Dist: google-generativeai>=0.3.0; extra == "genai"
